pandas_cache/__init__.py
pandas_cache/pandas_cache.py
pandas_cache/timer.py
pandas_cache-0.0.1.dist-info/METADATA
pandas_cache-0.0.1.dist-info/RECORD
pandas_cache-0.0.1.dist-info/WHEEL
pandas_cache-0.0.1.dist-info/top_level.txt
